ccgenerator/__init__.py
ccgenerator-0.0.3.dist-info/LICENSE
ccgenerator-0.0.3.dist-info/METADATA
ccgenerator-0.0.3.dist-info/WHEEL
ccgenerator-0.0.3.dist-info/top_level.txt
ccgenerator-0.0.3.dist-info/RECORD
