Metadata-Version: 2.1
Name: ccgenerator
Version: 0.0.3
Summary: Python Client to generate certificates of completion.
Home-page: https://github.com/mateusmuller/certificate-generator-pypi
Author: Mateus Muller
Author-email: mateusmuller2@gmail.com
License: MIT
Platform: UNKNOWN
Classifier: Intended Audience :: Developers
Classifier: License :: OSI Approved :: MIT License
Classifier: Natural Language :: English
Classifier: Programming Language :: Python :: 3
License-File: LICENSE
Requires-Dist: Pillow
